hcve_lib/__init__.py
hcve_lib/__tests__/__init__.py
hcve_lib/__tests__/test.R
hcve_lib/__tests__/test_cohort_statistics.py
hcve_lib/__tests__/test_context.py
hcve_lib/__tests__/test_cv.py
hcve_lib/__tests__/test_data.py
hcve_lib/__tests__/test_evaluation_functions.py
hcve_lib/__tests__/test_formatting.py
hcve_lib/__tests__/test_functional.py
hcve_lib/__tests__/test_metadata.py
hcve_lib/__tests__/test_metrics.py
hcve_lib/__tests__/test_pipelines.py
hcve_lib/__tests__/test_pipelines_utils.py
hcve_lib/__tests__/test_preprocessing.py
hcve_lib/__tests__/test_r_wrapper.py
hcve_lib/__tests__/test_serialization.py
hcve_lib/__tests__/test_splitting.py
hcve_lib/__tests__/test_survival.py
hcve_lib/__tests__/test_tracking.py
hcve_lib/__tests__/test_utils.py
hcve_lib/analysis.py
hcve_lib/cohort_statistics.py
hcve_lib/context.py
hcve_lib/custom_types.py
hcve_lib/cv.py
hcve_lib/data.py
hcve_lib/evaluation_functions.py
hcve_lib/feature_importance.py
hcve_lib/formatting.py
hcve_lib/functional.py
hcve_lib/log_output.py
hcve_lib/methods/__init__.py
hcve_lib/methods/__tests__/Adobe-communication.docx
hcve_lib/methods/__tests__/_test_balanced_xgboost.py
hcve_lib/methods/__tests__/pima_indians_diabetes.csv
hcve_lib/methods/__tests__/test_balanced_xgboost.py
hcve_lib/methods/balanced_xgboost.py
hcve_lib/methods/common.py
hcve_lib/metrics.py
hcve_lib/metrics_types.py
hcve_lib/missing.py
hcve_lib/notebook_init.ipynb
hcve_lib/optimization.py
hcve_lib/pipelines.py
hcve_lib/point_analysis.py
hcve_lib/preprocessing.py
hcve_lib/r_wrapper.py
hcve_lib/redirect.py
hcve_lib/serialization.py
hcve_lib/service_locator.py
hcve_lib/splitting.py
hcve_lib/statistics.py
hcve_lib/stats.py
hcve_lib/survival.py
hcve_lib/tracking.py
hcve_lib/transformers.py
hcve_lib/utils.py
hcve_lib/visualisation.py
hcve_lib/wrapped_sklearn.py
hcve_lib/wrapped_sksurv.py
hcve_lib-0.1.20.dist-info/METADATA
hcve_lib-0.1.20.dist-info/WHEEL
hcve_lib-0.1.20.dist-info/RECORD
