Metadata-Version: 2.1
Name: hcve-lib
Version: 0.1.20
Summary: 
Author: sitnarf
Author-email: sitnarf@gmail.com
Requires-Python: >=3.7,<4.0
Classifier: Programming Language :: Python :: 3
Classifier: Programming Language :: Python :: 3.7
Classifier: Programming Language :: Python :: 3.8
Classifier: Programming Language :: Python :: 3.9
Classifier: Programming Language :: Python :: 3.10
Classifier: Programming Language :: Python :: 3.11
Requires-Dist: Cython
Requires-Dist: Flask-SocketIO
Requires-Dist: ansi2html
Requires-Dist: dill
Requires-Dist: frozendict
Requires-Dist: imblearn
Requires-Dist: markupsafe (==2.0.1)
Requires-Dist: matplotlib
Requires-Dist: matplotlib-label-lines
Requires-Dist: mlflow
Requires-Dist: multimethod
Requires-Dist: notebook
Requires-Dist: numpy
Requires-Dist: optuna
Requires-Dist: pandas
Requires-Dist: plotly
Requires-Dist: pre-commit
Requires-Dist: pyaml
Requires-Dist: pyhumps
Requires-Dist: pytest
Requires-Dist: pytest-mock
Requires-Dist: rpy2
Requires-Dist: scikit-learn
Requires-Dist: statsmodels
Requires-Dist: toolz
Requires-Dist: torchtuples
Requires-Dist: xgboost
